pytodoist/__init__.py
pytodoist/api.py
pytodoist/todoist.py
pytodoist-2.1.4.dist-info/LICENCE.txt
pytodoist-2.1.4.dist-info/METADATA
pytodoist-2.1.4.dist-info/WHEEL
pytodoist-2.1.4.dist-info/top_level.txt
pytodoist-2.1.4.dist-info/RECORD
